{"moduleDefinition":{"range":[1,1,1,26],"value":{"type":"normal","normal":{"moduleName":{"range":[1,8,1,12],"value":["Main"]},"exposingList":{"range":[1,13,1,26],"value":{"type":"all","all":[1,23,1,25]}}}}},"imports":[{"range":[3,1,3,26],"value":{"moduleName":{"range":[3,8,3,12],"value":["Html"]},"moduleAlias":null,"exposingList":{"range":[3,13,3,26],"value":{"type":"all","all":[3,23,3,25]}}}},{"range":[4,1,4,33],"value":{"moduleName":{"range":[4,8,4,19],"value":["Html","Events"]},"moduleAlias":null,"exposingList":{"range":[4,20,4,33],"value":{"type":"all","all":[4,30,4,32]}}}},{"range":[5,1,5,37],"value":{"moduleName":{"range":[5,8,5,23],"value":["Html","Attributes"]},"moduleAlias":null,"exposingList":{"range":[5,24,5,37],"value":{"type":"all","all":[5,34,5,36]}}}}],"declarations":[{"range":[8,1,15,10],"value":{"type":"function","function":{"documentation":null,"signature":{"range":[8,1,8,31],"value":{"name":{"range":[8,1,8,5],"value":"main"},"typeAnnotation":{"range":[8,8,8,31],"value":{"type":"typed","typed":{"moduleNameAndName":{"range":[8,8,8,15],"value":{"moduleName":[],"name":"Program"}},"args":[{"range":[8,16,8,21],"value":{"type":"typed","typed":{"moduleNameAndName":{"range":[8,16,8,21],"value":{"moduleName":[],"name":"Never"}},"args":[]}}},{"range":[8,22,8,27],"value":{"type":"typed","typed":{"moduleNameAndName":{"range":[8,22,8,27],"value":{"moduleName":[],"name":"Model"}},"args":[]}}},{"range":[8,28,8,31],"value":{"type":"typed","typed":{"moduleNameAndName":{"range":[8,28,8,31],"value":{"moduleName":[],"name":"Msg"}},"args":[]}}}]}}}}},"declaration":{"range":[9,1,15,10],"value":{"name":{"range":[9,1,9,5],"value":"main"},"arguments":[],"expression":{"range":[10,5,15,10],"value":{"type":"application","application":[{"range":[10,5,10,17],"value":{"type":"functionOrValue","functionOrValue":{"moduleName":["Html"],"name":"program"}}},{"range":[11,9,15,10],"value":{"type":"record","record":[{"range":[11,11,11,22],"value":{"field":{"range":[11,11,11,15],"value":"init"},"expression":{"range":[11,18,11,22],"value":{"type":"functionOrValue","functionOrValue":{"moduleName":[],"name":"init"}}}}},{"range":[12,11,13,9],"value":{"field":{"range":[12,11,12,15],"value":"view"},"expression":{"range":[12,18,12,22],"value":{"type":"functionOrValue","functionOrValue":{"moduleName":[],"name":"view"}}}}},{"range":[13,11,14,9],"value":{"field":{"range":[13,11,13,17],"value":"update"},"expression":{"range":[13,20,13,26],"value":{"type":"functionOrValue","functionOrValue":{"moduleName":[],"name":"update"}}}}},{"range":[14,11,15,9],"value":{"field":{"range":[14,11,14,24],"value":"subscriptions"},"expression":{"range":[14,27,14,40],"value":{"type":"functionOrValue","functionOrValue":{"moduleName":[],"name":"subscriptions"}}}}}]}}]}}}}}}},{"range":[18,1,23,6],"value":{"type":"typeAlias","typeAlias":{"documentation":null,"name":{"range":[18,12,18,17],"value":"Model"},"generics":[],"typeAnnotation":{"range":[19,5,23,6],"value":{"type":"record","record":{"value":[{"range":[19,7,19,39],"value":{"name":{"range":[19,7,19,21],"value":"processedNotes"},"typeAnnotation":{"range":[19,24,19,39],"value":{"type":"typed","typed":{"moduleNameAndName":{"range":[19,24,19,28],"value":{"moduleName":[],"name":"List"}},"args":[{"range":[19,29,19,39],"value":{"type":"typed","typed":{"moduleNameAndName":{"range":[19,30,19,34],"value":{"moduleName":[],"name":"List"}},"args":[{"range":[19,35,19,38],"value":{"type":"typed","typed":{"moduleNameAndName":{"range":[19,35,19,38],"value":{"moduleName":[],"name":"Tab"}},"args":[]}}}]}}}]}}}}},{"range":[20,5,21,5],"value":{"name":{"range":[20,7,20,19],"value":"enteredNotes"},"typeAnnotation":{"range":[20,22,20,33],"value":{"type":"typed","typed":{"moduleNameAndName":{"range":[20,22,20,26],"value":{"moduleName":[],"name":"List"}},"args":[{"range":[20,27,20,33],"value":{"type":"typed","typed":{"moduleNameAndName":{"range":[20,27,20,33],"value":{"moduleName":[],"name":"String"}},"args":[]}}}]}}}}},{"range":[21,5,22,5],"value":{"name":{"range":[21,7,21,14],"value":"tabXpos"},"typeAnnotation":{"range":[21,17,21,20],"value":{"type":"typed","typed":{"moduleNameAndName":{"range":[21,17,21,20],"value":{"moduleName":[],"name":"Int"}},"args":[]}}}}},{"range":[22,5,23,5],"value":{"name":{"range":[22,7,22,14],"value":"tabYpos"},"typeAnnotation":{"range":[22,17,22,20],"value":{"type":"typed","typed":{"moduleNameAndName":{"range":[22,17,22,20],"value":{"moduleName":[],"name":"Int"}},"args":[]}}}}}]}}}}}},{"range":[26,1,32,13],"value":{"type":"function","function":{"documentation":null,"signature":null,"declaration":{"range":[26,1,32,13],"value":{"name":{"range":[26,1,26,5],"value":"init"},"arguments":[],"expression":{"range":[27,5,32,13],"value":{"type":"application","application":[{"range":[27,5,31,6],"value":{"type":"record","record":[{"range":[27,7,27,26],"value":{"field":{"range":[27,7,27,21],"value":"processedNotes"},"expression":{"range":[27,24,27,26],"value":{"type":"list","list":[]}}}},{"range":[28,7,29,5],"value":{"field":{"range":[28,7,28,19],"value":"enteredNotes"},"expression":{"range":[28,22,28,24],"value":{"type":"list","list":[]}}}},{"range":[29,7,30,5],"value":{"field":{"range":[29,7,29,14],"value":"tabXpos"},"expression":{"range":[29,17,29,18],"value":{"type":"integer","integer":0}}}},{"range":[30,7,31,5],"value":{"field":{"range":[30,7,30,14],"value":"tabYpos"},"expression":{"range":[30,17,30,18],"value":{"type":"integer","integer":0}}}}]}},{"range":[32,9,32,10],"value":{"type":"operator","operator":"!"}},{"range":[32,11,32,13],"value":{"type":"list","list":[]}}]}}}}}}},{"range":[35,1,38,6],"value":{"type":"typeAlias","typeAlias":{"documentation":null,"name":{"range":[35,12,35,15],"value":"Tab"},"generics":[],"typeAnnotation":{"range":[36,5,38,6],"value":{"type":"record","record":{"value":[{"range":[36,7,36,17],"value":{"name":{"range":[36,7,36,11],"value":"fret"},"typeAnnotation":{"range":[36,14,36,17],"value":{"type":"typed","typed":{"moduleNameAndName":{"range":[36,14,36,17],"value":{"moduleName":[],"name":"Int"}},"args":[]}}}}},{"range":[37,5,38,5],"value":{"name":{"range":[37,7,37,13],"value":"string"},"typeAnnotation":{"range":[37,16,37,19],"value":{"type":"typed","typed":{"moduleNameAndName":{"range":[37,16,37,19],"value":{"moduleName":[],"name":"Int"}},"args":[]}}}}}]}}}}}},{"range":[41,1,42,13],"value":{"type":"typeAlias","typeAlias":{"documentation":null,"name":{"range":[41,12,41,17],"value":"Chord"},"generics":[],"typeAnnotation":{"range":[42,5,42,13],"value":{"type":"typed","typed":{"moduleNameAndName":{"range":[42,5,42,9],"value":{"moduleName":[],"name":"List"}},"args":[{"range":[42,10,42,13],"value":{"type":"typed","typed":{"moduleNameAndName":{"range":[42,10,42,13],"value":{"moduleName":[],"name":"Tab"}},"args":[]}}}]}}}}}},{"range":[45,1,48,21],"value":{"type":"typedecl","typedecl":{"documentation":null,"name":{"range":[45,6,45,9],"value":"Msg"},"generics":[],"constructors":[{"range":[46,7,46,15],"value":{"name":{"range":[46,7,46,15],"value":"ClearTab"},"arguments":[]}},{"range":[47,7,47,15],"value":{"name":{"range":[47,7,47,15],"value":"NewStaff"},"arguments":[]}},{"range":[48,7,48,21],"value":{"name":{"range":[48,7,48,14],"value":"ReadTab"},"arguments":[{"range":[48,15,48,21],"value":{"type":"typed","typed":{"moduleNameAndName":{"range":[48,15,48,21],"value":{"moduleName":[],"name":"String"}},"args":[]}}}]}}]}}},{"range":[51,1,71,49],"value":{"type":"function","function":{"documentation":null,"signature":null,"declaration":{"range":[51,1,71,49],"value":{"name":{"range":[51,1,51,7],"value":"update"},"arguments":[{"range":[51,8,51,11],"value":{"type":"var","var":{"value":"msg"}}},{"range":[51,12,51,17],"value":{"type":"var","var":{"value":"model"}}}],"expression":{"range":[52,5,71,49],"value":{"type":"case","case":{"cases":[{"pattern":{"range":[53,9,53,17],"value":{"type":"named","named":{"qualified":{"moduleName":[],"name":"NewStaff"},"patterns":[]}}},"expression":{"range":[54,13,54,59],"value":{"type":"application","application":[{"range":[54,13,54,54],"value":{"type":"recordUpdate","recordUpdate":{"name":{"range":[54,15,54,20],"value":"model"},"updates":[{"range":[54,23,54,53],"value":{"field":{"range":[54,23,54,30],"value":"tabXpos"},"expression":{"range":[54,38,54,52],"value":{"type":"application","application":[{"range":[54,38,54,46],"value":{"type":"recordAccess","recordAccess":{"expression":{"range":[54,33,54,38],"value":{"type":"functionOrValue","functionOrValue":{"moduleName":[],"name":"model"}}},"name":{"range":[54,39,54,46],"value":"tabXpos"}}}},{"range":[54,47,54,48],"value":{"type":"operator","operator":"+"}},{"range":[54,49,54,52],"value":{"type":"integer","integer":200}}]}}}}]}}},{"range":[54,55,54,56],"value":{"type":"operator","operator":"!"}},{"range":[54,57,54,59],"value":{"type":"list","list":[]}}]}}},{"pattern":{"range":[56,9,56,22],"value":{"type":"named","named":{"qualified":{"moduleName":[],"name":"ReadTab"},"patterns":[{"range":[56,17,56,22],"value":{"type":"var","var":{"value":"notes"}}}]}}},"expression":{"range":[57,13,70,9],"value":{"type":"let","let":{"declarations":[{"range":[58,17,61,17],"value":{"type":"function","function":{"documentation":null,"signature":null,"declaration":{"range":[58,17,59,43],"value":{"name":{"range":[58,17,58,26],"value":"readNotes"},"arguments":[],"expression":{"range":[59,21,59,43],"value":{"type":"application","application":[{"range":[59,21,59,33],"value":{"type":"functionOrValue","functionOrValue":{"moduleName":["String"],"name":"split"}}},{"range":[59,34,59,37],"value":{"type":"literal","literal":" "}},{"range":[59,38,59,43],"value":{"type":"functionOrValue","functionOrValue":{"moduleName":[],"name":"notes"}}}]}}}}}}},{"range":[61,17,64,17],"value":{"type":"function","function":{"documentation":null,"signature":null,"declaration":{"range":[61,17,62,41],"value":{"name":{"range":[61,17,61,28],"value":"parsedNotes"},"arguments":[],"expression":{"range":[62,21,62,41],"value":{"type":"application","application":[{"range":[62,21,62,31],"value":{"type":"functionOrValue","functionOrValue":{"moduleName":[],"name":"parseInput"}}},{"range":[62,32,62,41],"value":{"type":"functionOrValue","functionOrValue":{"moduleName":[],"name":"readNotes"}}}]}}}}}}},{"range":[64,17,66,13],"value":{"type":"function","function":{"documentation":null,"signature":null,"declaration":{"range":[64,17,65,39],"value":{"name":{"range":[64,17,64,21],"value":"yPos"},"arguments":[],"expression":{"range":[65,26,65,39],"value":{"type":"application","application":[{"range":[65,26,65,34],"value":{"type":"recordAccess","recordAccess":{"expression":{"range":[65,21,65,26],"value":{"type":"functionOrValue","functionOrValue":{"moduleName":[],"name":"model"}}},"name":{"range":[65,27,65,34],"value":"tabYpos"}}}},{"range":[65,35,65,36],"value":{"type":"operator","operator":"+"}},{"range":[65,37,65,39],"value":{"type":"integer","integer":20}}]}}}}}}}],"expression":{"range":[67,17,68,25],"value":{"type":"application","application":[{"range":[67,17,67,99],"value":{"type":"recordUpdate","recordUpdate":{"name":{"range":[67,19,67,24],"value":"model"},"updates":[{"range":[67,27,67,51],"value":{"field":{"range":[67,27,67,39],"value":"enteredNotes"},"expression":{"range":[67,42,67,51],"value":{"type":"functionOrValue","functionOrValue":{"moduleName":[],"name":"readNotes"}}}}},{"range":[67,53,67,81],"value":{"field":{"range":[67,53,67,67],"value":"processedNotes"},"expression":{"range":[67,70,67,81],"value":{"type":"functionOrValue","functionOrValue":{"moduleName":[],"name":"parsedNotes"}}}}},{"range":[67,83,67,98],"value":{"field":{"range":[67,83,67,90],"value":"tabYpos"},"expression":{"range":[67,93,67,97],"value":{"type":"functionOrValue","functionOrValue":{"moduleName":[],"name":"yPos"}}}}}]}}},{"range":[68,21,68,22],"value":{"type":"operator","operator":"!"}},{"range":[68,23,68,25],"value":{"type":"list","list":[]}}]}}}}}},{"pattern":{"range":[70,9,70,17],"value":{"type":"named","named":{"qualified":{"moduleName":[],"name":"ClearTab"},"patterns":[]}}},"expression":{"range":[71,13,71,49],"value":{"type":"application","application":[{"range":[71,13,71,44],"value":{"type":"recordUpdate","recordUpdate":{"name":{"range":[71,15,71,20],"value":"model"},"updates":[{"range":[71,23,71,43],"value":{"field":{"range":[71,23,71,37],"value":"processedNotes"},"expression":{"range":[71,40,71,42],"value":{"type":"list","list":[]}}}}]}}},{"range":[71,45,71,46],"value":{"type":"operator","operator":"!"}},{"range":[71,47,71,49],"value":{"type":"list","list":[]}}]}}}],"expression":{"range":[52,10,52,13],"value":{"type":"functionOrValue","functionOrValue":{"moduleName":[],"name":"msg"}}}}}}}}}}},{"range":[74,1,82,10],"value":{"type":"function","function":{"documentation":null,"signature":{"range":[74,1,74,25],"value":{"name":{"range":[74,1,74,5],"value":"view"},"typeAnnotation":{"range":[74,8,74,25],"value":{"type":"function","function":{"left":{"range":[74,8,74,13],"value":{"type":"typed","typed":{"moduleNameAndName":{"range":[74,8,74,13],"value":{"moduleName":[],"name":"Model"}},"args":[]}}},"right":{"range":[74,17,74,25],"value":{"type":"typed","typed":{"moduleNameAndName":{"range":[74,17,74,21],"value":{"moduleName":[],"name":"Html"}},"args":[{"range":[74,22,74,25],"value":{"type":"typed","typed":{"moduleNameAndName":{"range":[74,22,74,25],"value":{"moduleName":[],"name":"Msg"}},"args":[]}}}]}}}}}}}},"declaration":{"range":[75,1,82,10],"value":{"name":{"range":[75,1,75,5],"value":"view"},"arguments":[{"range":[75,6,75,11],"value":{"type":"var","var":{"value":"model"}}}],"expression":{"range":[76,5,82,10],"value":{"type":"application","application":[{"range":[76,5,76,8],"value":{"type":"functionOrValue","functionOrValue":{"moduleName":[],"name":"div"}}},{"range":[76,9,76,69],"value":{"type":"list","list":[{"range":[76,11,76,67],"value":{"type":"application","application":[{"range":[76,11,76,16],"value":{"type":"functionOrValue","functionOrValue":{"moduleName":[],"name":"style"}}},{"range":[76,17,76,67],"value":{"type":"list","list":[{"range":[76,19,76,38],"value":{"type":"tupled","tupled":[{"range":[76,21,76,28],"value":{"type":"literal","literal":"color"}},{"range":[76,30,76,36],"value":{"type":"literal","literal":"#333"}}]}},{"range":[76,40,76,65],"value":{"type":"tupled","tupled":[{"range":[76,42,76,53],"value":{"type":"literal","literal":"textAlign"}},{"range":[76,55,76,63],"value":{"type":"literal","literal":"center"}}]}}]}}]}}]}},{"range":[77,9,82,10],"value":{"type":"list","list":[{"range":[77,11,77,19],"value":{"type":"functionOrValue","functionOrValue":{"moduleName":[],"name":"tabInput"}}},{"range":[78,11,78,22],"value":{"type":"functionOrValue","functionOrValue":{"moduleName":[],"name":"clearButton"}}},{"range":[79,11,79,19],"value":{"type":"functionOrValue","functionOrValue":{"moduleName":[],"name":"tabLines"}}},{"range":[80,11,80,40],"value":{"type":"application","application":[{"range":[80,11,80,19],"value":{"type":"functionOrValue","functionOrValue":{"moduleName":[],"name":"tabNotes"}}},{"range":[80,25,80,40],"value":{"type":"recordAccess","recordAccess":{"expression":{"range":[80,20,80,25],"value":{"type":"functionOrValue","functionOrValue":{"moduleName":[],"name":"model"}}},"name":{"range":[80,26,80,40],"value":"processedNotes"}}}}]}},{"range":[81,11,81,23],"value":{"type":"functionOrValue","functionOrValue":{"moduleName":[],"name":"instructions"}}}]}}]}}}}}}},{"range":[87,1,135,1],"value":{"type":"function","function":{"documentation":null,"signature":{"range":[87,1,87,39],"value":{"name":{"range":[87,1,87,9],"value":"tabNotes"},"typeAnnotation":{"range":[87,12,87,39],"value":{"type":"function","function":{"left":{"range":[87,12,87,27],"value":{"type":"typed","typed":{"moduleNameAndName":{"range":[87,12,87,16],"value":{"moduleName":[],"name":"List"}},"args":[{"range":[87,17,87,27],"value":{"type":"typed","typed":{"moduleNameAndName":{"range":[87,18,87,22],"value":{"moduleName":[],"name":"List"}},"args":[{"range":[87,23,87,26],"value":{"type":"typed","typed":{"moduleNameAndName":{"range":[87,23,87,26],"value":{"moduleName":[],"name":"Tab"}},"args":[]}}}]}}}]}}},"right":{"range":[87,31,87,39],"value":{"type":"typed","typed":{"moduleNameAndName":{"range":[87,31,87,35],"value":{"moduleName":[],"name":"Html"}},"args":[{"range":[87,36,87,39],"value":{"type":"typed","typed":{"moduleNameAndName":{"range":[87,36,87,39],"value":{"moduleName":[],"name":"Msg"}},"args":[]}}}]}}}}}}}},"declaration":{"range":[88,1,135,1],"value":{"name":{"range":[88,1,88,9],"value":"tabNotes"},"arguments":[{"range":[88,10,88,17],"value":{"type":"var","var":{"value":"tabList"}}}],"expression":{"range":[89,5,135,1],"value":{"type":"let","let":{"declarations":[{"range":[90,9,130,5],"value":{"type":"function","function":{"documentation":null,"signature":null,"declaration":{"range":[90,9,130,5],"value":{"name":{"range":[90,9,90,16],"value":"tabItem"},"arguments":[{"range":[90,17,90,18],"value":{"type":"var","var":{"value":"a"}}}],"expression":{"range":[92,13,130,5],"value":{"type":"ifBlock","ifBlock":{"clause":{"range":[92,16,92,34],"value":{"type":"application","application":[{"range":[92,16,92,27],"value":{"type":"functionOrValue","functionOrValue":{"moduleName":["List"],"name":"length"}}},{"range":[92,28,92,29],"value":{"type":"functionOrValue","functionOrValue":{"moduleName":[],"name":"a"}}},{"range":[92,30,92,32],"value":{"type":"operator","operator":"=="}},{"range":[92,33,92,34],"value":{"type":"integer","integer":1}}]}},"then":{"range":[93,17,118,13],"value":{"type":"let","let":{"declarations":[{"range":[94,21,97,17],"value":{"type":"function","function":{"documentation":null,"signature":null,"declaration":{"range":[94,21,96,74],"value":{"name":{"range":[94,21,94,25],"value":"note"},"arguments":[],"expression":{"range":[95,25,96,74],"value":{"type":"application","application":[{"range":[95,25,95,34],"value":{"type":"functionOrValue","functionOrValue":{"moduleName":["List"],"name":"head"}}},{"range":[95,35,95,36],"value":{"type":"functionOrValue","functionOrValue":{"moduleName":[],"name":"a"}}},{"range":[96,29,96,31],"value":{"type":"operator","operator":"|>"}},{"range":[96,32,96,49],"value":{"type":"functionOrValue","functionOrValue":{"moduleName":["Maybe"],"name":"withDefault"}}},{"range":[96,50,96,74],"value":{"type":"record","record":[{"range":[96,52,96,60],"value":{"field":{"range":[96,52,96,56],"value":"fret"},"expression":{"range":[96,59,96,60],"value":{"type":"integer","integer":0}}}},{"range":[96,62,96,73],"value":{"field":{"range":[96,62,96,68],"value":"string"},"expression":{"range":[96,71,96,72],"value":{"type":"integer","integer":1}}}}]}}]}}}}}}}],"expression":{"range":[98,21,118,13],"value":{"type":"ifBlock","ifBlock":{"clause":{"range":[98,28,98,39],"value":{"type":"application","application":[{"range":[98,28,98,33],"value":{"type":"recordAccess","recordAccess":{"expression":{"range":[98,24,98,28],"value":{"type":"functionOrValue","functionOrValue":{"moduleName":[],"name":"note"}}},"name":{"range":[98,29,98,33],"value":"fret"}}}},{"range":[98,34,98,36],"value":{"type":"operator","operator":"=="}},{"range":[98,37,98,39],"value":{"type":"integer","integer":50}}]}},"then":{"range":[99,25,99,84],"value":{"type":"application","application":[{"range":[99,25,99,28],"value":{"type":"functionOrValue","functionOrValue":{"moduleName":[],"name":"div"}}},{"range":[99,29,99,71],"value":{"type":"list","list":[{"range":[99,31,99,69],"value":{"type":"application","application":[{"range":[99,31,99,36],"value":{"type":"functionOrValue","functionOrValue":{"moduleName":[],"name":"style"}}},{"range":[99,37,99,69],"value":{"type":"list","list":[{"range":[99,39,99,67],"value":{"type":"tupled","tupled":[{"range":[99,41,99,48],"value":{"type":"literal","literal":"color"}},{"range":[99,50,99,65],"value":{"type":"literal","literal":"rgba(0,0,0,0)"}}]}}]}}]}}]}},{"range":[99,72,99,84],"value":{"type":"list","list":[{"range":[99,74,99,82],"value":{"type":"application","application":[{"range":[99,74,99,78],"value":{"type":"functionOrValue","functionOrValue":{"moduleName":[],"name":"text"}}},{"range":[99,79,99,82],"value":{"type":"literal","literal":"-"}}]}}]}}]}},"else":{"range":[100,26,118,13],"value":{"type":"ifBlock","ifBlock":{"clause":{"range":[100,33,100,45],"value":{"type":"application","application":[{"range":[100,33,100,40],"value":{"type":"recordAccess","recordAccess":{"expression":{"range":[100,29,100,33],"value":{"type":"functionOrValue","functionOrValue":{"moduleName":[],"name":"note"}}},"name":{"range":[100,34,100,40],"value":"string"}}}},{"range":[100,41,100,43],"value":{"type":"operator","operator":"=="}},{"range":[100,44,100,45],"value":{"type":"integer","integer":9}}]}},"then":{"range":[102,25,102,149],"value":{"type":"application","application":[{"range":[102,25,102,28],"value":{"type":"functionOrValue","functionOrValue":{"moduleName":[],"name":"div"}}},{"range":[102,29,102,146],"value":{"type":"list","list":[{"range":[102,31,102,144],"value":{"type":"application","application":[{"range":[102,31,102,36],"value":{"type":"functionOrValue","functionOrValue":{"moduleName":[],"name":"style"}}},{"range":[102,37,102,144],"value":{"type":"list","list":[{"range":[102,39,102,59],"value":{"type":"tupled","tupled":[{"range":[102,41,102,49],"value":{"type":"literal","literal":"height"}},{"range":[102,51,102,57],"value":{"type":"literal","literal":"85px"}}]}},{"range":[102,61,102,91],"value":{"type":"tupled","tupled":[{"range":[102,63,102,71],"value":{"type":"literal","literal":"border"}},{"range":[102,73,102,89],"value":{"type":"literal","literal":"1px solid #aaa"}}]}},{"range":[102,93,102,110],"value":{"type":"tupled","tupled":[{"range":[102,95,102,103],"value":{"type":"literal","literal":"zIndex"}},{"range":[102,105,102,108],"value":{"type":"literal","literal":"1"}}]}},{"range":[102,112,102,142],"value":{"type":"tupled","tupled":[{"range":[102,114,102,122],"value":{"type":"literal","literal":"margin"}},{"range":[102,124,102,140],"value":{"type":"literal","literal":"5px 5px 0 15px"}}]}}]}}]}}]}},{"range":[102,147,102,149],"value":{"type":"list","list":[]}}]}},"else":{"range":[103,26,118,13],"value":{"type":"ifBlock","ifBlock":{"clause":{"range":[103,33,103,45],"value":{"type":"application","application":[{"range":[103,33,103,40],"value":{"type":"recordAccess","recordAccess":{"expression":{"range":[103,29,103,33],"value":{"type":"functionOrValue","functionOrValue":{"moduleName":[],"name":"note"}}},"name":{"range":[103,34,103,40],"value":"string"}}}},{"range":[103,41,103,43],"value":{"type":"operator","operator":"=="}},{"range":[103,44,103,45],"value":{"type":"integer","integer":8}}]}},"then":{"range":[105,25,105,210],"value":{"type":"application","application":[{"range":[105,25,105,28],"value":{"type":"functionOrValue","functionOrValue":{"moduleName":[],"name":"div"}}},{"range":[105,29,105,207],"value":{"type":"list","list":[{"range":[105,31,105,205],"value":{"type":"application","application":[{"range":[105,31,105,36],"value":{"type":"functionOrValue","functionOrValue":{"moduleName":[],"name":"style"}}},{"range":[105,37,105,205],"value":{"type":"list","list":[{"range":[105,39,105,59],"value":{"type":"tupled","tupled":[{"range":[105,41,105,49],"value":{"type":"literal","literal":"height"}},{"range":[105,51,105,57],"value":{"type":"literal","literal":"85px"}}]}},{"range":[105,61,105,79],"value":{"type":"tupled","tupled":[{"range":[105,63,105,70],"value":{"type":"literal","literal":"width"}},{"range":[105,72,105,77],"value":{"type":"literal","literal":"3px"}}]}},{"range":[105,81,105,115],"value":{"type":"tupled","tupled":[{"range":[105,83,105,95],"value":{"type":"literal","literal":"borderLeft"}},{"range":[105,97,105,113],"value":{"type":"literal","literal":"2px solid #aaa"}}]}},{"range":[105,117,105,152],"value":{"type":"tupled","tupled":[{"range":[105,119,105,132],"value":{"type":"literal","literal":"borderRight"}},{"range":[105,134,105,150],"value":{"type":"literal","literal":"2px solid #aaa"}}]}},{"range":[105,154,105,171],"value":{"type":"tupled","tupled":[{"range":[105,156,105,164],"value":{"type":"literal","literal":"zIndex"}},{"range":[105,166,105,169],"value":{"type":"literal","literal":"1"}}]}},{"range":[105,173,105,203],"value":{"type":"tupled","tupled":[{"range":[105,175,105,183],"value":{"type":"literal","literal":"margin"}},{"range":[105,185,105,201],"value":{"type":"literal","literal":"5px 5px 0 15px"}}]}}]}}]}}]}},{"range":[105,208,105,210],"value":{"type":"list","list":[]}}]}},"else":{"range":[106,26,118,13],"value":{"type":"ifBlock","ifBlock":{"clause":{"range":[106,33,106,44],"value":{"type":"application","application":[{"range":[106,33,106,38],"value":{"type":"recordAccess","recordAccess":{"expression":{"range":[106,29,106,33],"value":{"type":"functionOrValue","functionOrValue":{"moduleName":[],"name":"note"}}},"name":{"range":[106,34,106,38],"value":"fret"}}}},{"range":[106,39,106,41],"value":{"type":"operator","operator":"=="}},{"range":[106,42,106,44],"value":{"type":"integer","integer":51}}]}},"then":{"range":[108,25,108,163],"value":{"type":"application","application":[{"range":[108,25,108,28],"value":{"type":"functionOrValue","functionOrValue":{"moduleName":[],"name":"div"}}},{"range":[108,29,108,150],"value":{"type":"list","list":[{"range":[108,31,108,148],"value":{"type":"application","application":[{"range":[108,31,108,36],"value":{"type":"functionOrValue","functionOrValue":{"moduleName":[],"name":"style"}}},{"range":[108,37,108,148],"value":{"type":"list","list":[{"range":[108,39,108,105],"value":{"type":"tupled","tupled":[{"range":[108,41,108,52],"value":{"type":"literal","literal":"transform"}},{"range":[108,54,108,103],"value":{"type":"literal","literal":"rotate(-90deg) translateX(10px) translateY(6px)"}}]}},{"range":[108,107,108,146],"value":{"type":"tupled","tupled":[{"range":[108,109,108,120],"value":{"type":"literal","literal":"marginTop"}},{"range":[108,122,108,144],"value":{"type":"parenthesized","parenthesized":{"range":[108,123,108,143],"value":{"type":"application","application":[{"range":[108,123,108,131],"value":{"type":"functionOrValue","functionOrValue":{"moduleName":[],"name":"noteXpos"}}},{"range":[108,136,108,143],"value":{"type":"recordAccess","recordAccess":{"expression":{"range":[108,132,108,136],"value":{"type":"functionOrValue","functionOrValue":{"moduleName":[],"name":"note"}}},"name":{"range":[108,137,108,143],"value":"string"}}}}]}}}}]}}]}}]}}]}},{"range":[108,151,108,163],"value":{"type":"list","list":[{"range":[108,153,108,161],"value":{"type":"application","application":[{"range":[108,153,108,157],"value":{"type":"functionOrValue","functionOrValue":{"moduleName":[],"name":"text"}}},{"range":[108,158,108,161],"value":{"type":"literal","literal":")"}}]}}]}}]}},"else":{"range":[109,26,118,13],"value":{"type":"ifBlock","ifBlock":{"clause":{"range":[109,33,109,44],"value":{"type":"application","application":[{"range":[109,33,109,38],"value":{"type":"recordAccess","recordAccess":{"expression":{"range":[109,29,109,33],"value":{"type":"functionOrValue","functionOrValue":{"moduleName":[],"name":"note"}}},"name":{"range":[109,34,109,38],"value":"fret"}}}},{"range":[109,39,109,41],"value":{"type":"operator","operator":"=="}},{"range":[109,42,109,44],"value":{"type":"integer","integer":52}}]}},"then":{"range":[111,25,111,141],"value":{"type":"application","application":[{"range":[111,25,111,28],"value":{"type":"functionOrValue","functionOrValue":{"moduleName":[],"name":"div"}}},{"range":[111,29,111,128],"value":{"type":"list","list":[{"range":[111,31,111,126],"value":{"type":"application","application":[{"range":[111,31,111,36],"value":{"type":"functionOrValue","functionOrValue":{"moduleName":[],"name":"style"}}},{"range":[111,37,111,126],"value":{"type":"list","list":[{"range":[111,39,111,71],"value":{"type":"tupled","tupled":[{"range":[111,41,111,52],"value":{"type":"literal","literal":"transform"}},{"range":[111,54,111,69],"value":{"type":"literal","literal":"skewX(-45deg)"}}]}},{"range":[111,73,111,124],"value":{"type":"tupled","tupled":[{"range":[111,75,111,83],"value":{"type":"literal","literal":"margin"}},{"range":[111,85,111,122],"value":{"type":"application","application":[{"range":[111,85,111,107],"value":{"type":"parenthesized","parenthesized":{"range":[111,86,111,106],"value":{"type":"application","application":[{"range":[111,86,111,94],"value":{"type":"functionOrValue","functionOrValue":{"moduleName":[],"name":"noteXpos"}}},{"range":[111,99,111,106],"value":{"type":"recordAccess","recordAccess":{"expression":{"range":[111,95,111,99],"value":{"type":"functionOrValue","functionOrValue":{"moduleName":[],"name":"note"}}},"name":{"range":[111,100,111,106],"value":"string"}}}}]}}}},{"range":[111,108,111,110],"value":{"type":"operator","operator":"++"}},{"range":[111,111,111,122],"value":{"type":"literal","literal":" 0 0 10px"}}]}}]}}]}}]}}]}},{"range":[111,129,111,141],"value":{"type":"list","list":[{"range":[111,131,111,139],"value":{"type":"application","application":[{"range":[111,131,111,135],"value":{"type":"functionOrValue","functionOrValue":{"moduleName":[],"name":"text"}}},{"range":[111,136,111,139],"value":{"type":"literal","literal":"|"}}]}}]}}]}},"else":{"range":[112,26,118,13],"value":{"type":"ifBlock","ifBlock":{"clause":{"range":[112,33,112,44],"value":{"type":"application","application":[{"range":[112,33,112,38],"value":{"type":"recordAccess","recordAccess":{"expression":{"range":[112,29,112,33],"value":{"type":"functionOrValue","functionOrValue":{"moduleName":[],"name":"note"}}},"name":{"range":[112,34,112,38],"value":"fret"}}}},{"range":[112,39,112,41],"value":{"type":"operator","operator":"=="}},{"range":[112,42,112,44],"value":{"type":"integer","integer":53}}]}},"then":{"range":[114,25,114,140],"value":{"type":"application","application":[{"range":[114,25,114,28],"value":{"type":"functionOrValue","functionOrValue":{"moduleName":[],"name":"div"}}},{"range":[114,29,114,127],"value":{"type":"list","list":[{"range":[114,31,114,125],"value":{"type":"application","application":[{"range":[114,31,114,36],"value":{"type":"functionOrValue","functionOrValue":{"moduleName":[],"name":"style"}}},{"range":[114,37,114,125],"value":{"type":"list","list":[{"range":[114,39,114,70],"value":{"type":"tupled","tupled":[{"range":[114,41,114,52],"value":{"type":"literal","literal":"transform"}},{"range":[114,54,114,68],"value":{"type":"literal","literal":"skewX(45deg)"}}]}},{"range":[114,72,114,123],"value":{"type":"tupled","tupled":[{"range":[114,74,114,82],"value":{"type":"literal","literal":"margin"}},{"range":[114,84,114,121],"value":{"type":"application","application":[{"range":[114,84,114,106],"value":{"type":"parenthesized","parenthesized":{"range":[114,85,114,105],"value":{"type":"application","application":[{"range":[114,85,114,93],"value":{"type":"functionOrValue","functionOrValue":{"moduleName":[],"name":"noteXpos"}}},{"range":[114,98,114,105],"value":{"type":"recordAccess","recordAccess":{"expression":{"range":[114,94,114,98],"value":{"type":"functionOrValue","functionOrValue":{"moduleName":[],"name":"note"}}},"name":{"range":[114,99,114,105],"value":"string"}}}}]}}}},{"range":[114,107,114,109],"value":{"type":"operator","operator":"++"}},{"range":[114,110,114,121],"value":{"type":"literal","literal":" 0 0 10px"}}]}}]}}]}}]}}]}},{"range":[114,128,114,140],"value":{"type":"list","list":[{"range":[114,130,114,138],"value":{"type":"application","application":[{"range":[114,130,114,134],"value":{"type":"functionOrValue","functionOrValue":{"moduleName":[],"name":"text"}}},{"range":[114,135,114,138],"value":{"type":"literal","literal":"|"}}]}}]}}]}},"else":{"range":[116,25,116,167],"value":{"type":"application","application":[{"range":[116,25,116,28],"value":{"type":"functionOrValue","functionOrValue":{"moduleName":[],"name":"div"}}},{"range":[116,29,116,136],"value":{"type":"list","list":[{"range":[116,31,116,134],"value":{"type":"application","application":[{"range":[116,31,116,36],"value":{"type":"functionOrValue","functionOrValue":{"moduleName":[],"name":"style"}}},{"range":[116,37,116,134],"value":{"type":"list","list":[{"range":[116,39,116,65],"value":{"type":"tupled","tupled":[{"range":[116,41,116,51],"value":{"type":"literal","literal":"position"}},{"range":[116,53,116,63],"value":{"type":"literal","literal":"relative"}}]}},{"range":[116,67,116,106],"value":{"type":"tupled","tupled":[{"range":[116,69,116,80],"value":{"type":"literal","literal":"marginTop"}},{"range":[116,82,116,104],"value":{"type":"parenthesized","parenthesized":{"range":[116,83,116,103],"value":{"type":"application","application":[{"range":[116,83,116,91],"value":{"type":"functionOrValue","functionOrValue":{"moduleName":[],"name":"noteXpos"}}},{"range":[116,96,116,103],"value":{"type":"recordAccess","recordAccess":{"expression":{"range":[116,92,116,96],"value":{"type":"functionOrValue","functionOrValue":{"moduleName":[],"name":"note"}}},"name":{"range":[116,97,116,103],"value":"string"}}}}]}}}}]}},{"range":[116,108,116,132],"value":{"type":"tupled","tupled":[{"range":[116,110,116,122],"value":{"type":"literal","literal":"marginLeft"}},{"range":[116,124,116,130],"value":{"type":"literal","literal":"10px"}}]}}]}}]}}]}},{"range":[116,137,116,167],"value":{"type":"list","list":[{"range":[116,139,116,165],"value":{"type":"application","application":[{"range":[116,139,116,143],"value":{"type":"functionOrValue","functionOrValue":{"moduleName":[],"name":"text"}}},{"range":[116,144,116,146],"value":{"type":"operator","operator":"<|"}},{"range":[116,147,116,155],"value":{"type":"functionOrValue","functionOrValue":{"moduleName":[],"name":"toString"}}},{"range":[116,160,116,165],"value":{"type":"recordAccess","recordAccess":{"expression":{"range":[116,156,116,160],"value":{"type":"functionOrValue","functionOrValue":{"moduleName":[],"name":"note"}}},"name":{"range":[116,161,116,165],"value":"fret"}}}}]}}]}}]}}}}}}}}}}}}}}}}}}}}}}},"else":{"range":[119,17,130,5],"value":{"type":"let","let":{"declarations":[{"range":[120,21,126,21],"value":{"type":"function","function":{"documentation":null,"signature":null,"declaration":{"range":[120,21,126,21],"value":{"name":{"range":[120,21,120,27],"value":"mapper"},"arguments":[{"range":[120,28,120,29],"value":{"type":"var","var":{"value":"b"}}}],"expression":{"range":[121,25,126,21],"value":{"type":"ifBlock","ifBlock":{"clause":{"range":[121,29,121,40],"value":{"type":"application","application":[{"range":[121,29,121,34],"value":{"type":"recordAccess","recordAccess":{"expression":{"range":[121,28,121,29],"value":{"type":"functionOrValue","functionOrValue":{"moduleName":[],"name":"b"}}},"name":{"range":[121,30,121,34],"value":"fret"}}}},{"range":[121,35,121,37],"value":{"type":"operator","operator":"=="}},{"range":[121,38,121,40],"value":{"type":"integer","integer":50}}]}},"then":{"range":[122,29,122,38],"value":{"type":"application","application":[{"range":[122,29,122,32],"value":{"type":"functionOrValue","functionOrValue":{"moduleName":[],"name":"div"}}},{"range":[122,33,122,35],"value":{"type":"list","list":[]}},{"range":[122,36,122,38],"value":{"type":"list","list":[]}}]}},"else":{"range":[124,29,124,104],"value":{"type":"application","application":[{"range":[124,29,124,32],"value":{"type":"functionOrValue","functionOrValue":{"moduleName":[],"name":"div"}}},{"range":[124,33,124,76],"value":{"type":"list","list":[{"range":[124,35,124,74],"value":{"type":"application","application":[{"range":[124,35,124,40],"value":{"type":"functionOrValue","functionOrValue":{"moduleName":[],"name":"style"}}},{"range":[124,41,124,74],"value":{"type":"list","list":[{"range":[124,43,124,72],"value":{"type":"tupled","tupled":[{"range":[124,45,124,53],"value":{"type":"literal","literal":"margin"}},{"range":[124,55,124,70],"value":{"type":"literal","literal":"-1px 0 0 10px"}}]}}]}}]}}]}},{"range":[124,77,124,104],"value":{"type":"list","list":[{"range":[124,79,124,102],"value":{"type":"application","application":[{"range":[124,79,124,83],"value":{"type":"functionOrValue","functionOrValue":{"moduleName":[],"name":"text"}}},{"range":[124,84,124,86],"value":{"type":"operator","operator":"<|"}},{"range":[124,87,124,95],"value":{"type":"functionOrValue","functionOrValue":{"moduleName":[],"name":"toString"}}},{"range":[124,97,124,102],"value":{"type":"recordAccess","recordAccess":{"expression":{"range":[124,96,124,97],"value":{"type":"functionOrValue","functionOrValue":{"moduleName":[],"name":"b"}}},"name":{"range":[124,98,124,102],"value":"fret"}}}}]}}]}}]}}}}}}}}}},{"range":[126,21,128,17],"value":{"type":"function","function":{"documentation":null,"signature":null,"declaration":{"range":[126,21,127,42],"value":{"name":{"range":[126,21,126,29],"value":"finalDiv"},"arguments":[],"expression":{"range":[127,25,127,42],"value":{"type":"application","application":[{"range":[127,25,127,33],"value":{"type":"functionOrValue","functionOrValue":{"moduleName":["List"],"name":"map"}}},{"range":[127,34,127,40],"value":{"type":"functionOrValue","functionOrValue":{"moduleName":[],"name":"mapper"}}},{"range":[127,41,127,42],"value":{"type":"functionOrValue","functionOrValue":{"moduleName":[],"name":"a"}}}]}}}}}}}],"expression":{"range":[129,21,129,89],"value":{"type":"application","application":[{"range":[129,21,129,24],"value":{"type":"functionOrValue","functionOrValue":{"moduleName":[],"name":"div"}}},{"range":[129,25,129,65],"value":{"type":"list","list":[{"range":[129,27,129,63],"value":{"type":"application","application":[{"range":[129,27,129,32],"value":{"type":"functionOrValue","functionOrValue":{"moduleName":[],"name":"style"}}},{"range":[129,33,129,63],"value":{"type":"list","list":[{"range":[129,35,129,61],"value":{"type":"tupled","tupled":[{"range":[129,37,129,47],"value":{"type":"literal","literal":"position"}},{"range":[129,49,129,59],"value":{"type":"literal","literal":"relative"}}]}}]}}]}}]}},{"range":[129,66,129,89],"value":{"type":"parenthesized","parenthesized":{"range":[129,67,129,88],"value":{"type":"application","application":[{"range":[129,67,129,79],"value":{"type":"functionOrValue","functionOrValue":{"moduleName":["List"],"name":"reverse"}}},{"range":[129,80,129,88],"value":{"type":"functionOrValue","functionOrValue":{"moduleName":[],"name":"finalDiv"}}}]}}}}]}}}}}}}}}}}}}],"expression":{"range":[131,9,132,39],"value":{"type":"application","application":[{"range":[131,9,131,12],"value":{"type":"functionOrValue","functionOrValue":{"moduleName":[],"name":"div"}}},{"range":[131,13,131,75],"value":{"type":"list","list":[{"range":[131,15,131,73],"value":{"type":"application","application":[{"range":[131,15,131,20],"value":{"type":"functionOrValue","functionOrValue":{"moduleName":[],"name":"style"}}},{"range":[131,21,131,73],"value":{"type":"list","list":[{"range":[131,23,131,44],"value":{"type":"tupled","tupled":[{"range":[131,25,131,34],"value":{"type":"literal","literal":"display"}},{"range":[131,36,131,42],"value":{"type":"literal","literal":"flex"}}]}},{"range":[131,46,131,71],"value":{"type":"tupled","tupled":[{"range":[131,48,131,59],"value":{"type":"literal","literal":"marginTop"}},{"range":[131,61,131,69],"value":{"type":"literal","literal":"-100px"}}]}}]}}]}}]}},{"range":[132,13,132,39],"value":{"type":"parenthesized","parenthesized":{"range":[132,14,132,38],"value":{"type":"application","application":[{"range":[132,14,132,22],"value":{"type":"functionOrValue","functionOrValue":{"moduleName":["List"],"name":"map"}}},{"range":[132,23,132,30],"value":{"type":"functionOrValue","functionOrValue":{"moduleName":[],"name":"tabItem"}}},{"range":[132,31,132,38],"value":{"type":"functionOrValue","functionOrValue":{"moduleName":[],"name":"tabList"}}}]}}}}]}}}}}}}}}},{"range":[135,1,151,1],"value":{"type":"function","function":{"documentation":null,"signature":{"range":[135,1,135,20],"value":{"name":{"range":[135,1,135,9],"value":"tabLines"},"typeAnnotation":{"range":[135,12,135,20],"value":{"type":"typed","typed":{"moduleNameAndName":{"range":[135,12,135,16],"value":{"moduleName":[],"name":"Html"}},"args":[{"range":[135,17,135,20],"value":{"type":"typed","typed":{"moduleNameAndName":{"range":[135,17,135,20],"value":{"moduleName":[],"name":"Msg"}},"args":[]}}}]}}}}},"declaration":{"range":[136,1,151,1],"value":{"name":{"range":[136,1,136,9],"value":"tabLines"},"arguments":[],"expression":{"range":[137,5,151,1],"value":{"type":"let","let":{"declarations":[{"range":[138,9,140,5],"value":{"type":"function","function":{"documentation":null,"signature":null,"declaration":{"range":[138,9,139,78],"value":{"name":{"range":[138,9,138,18],"value":"lineStyle"},"arguments":[],"expression":{"range":[139,13,139,78],"value":{"type":"application","application":[{"range":[139,13,139,18],"value":{"type":"functionOrValue","functionOrValue":{"moduleName":[],"name":"style"}}},{"range":[139,19,139,78],"value":{"type":"list","list":[{"range":[139,21,139,51],"value":{"type":"tupled","tupled":[{"range":[139,23,139,31],"value":{"type":"literal","literal":"border"}},{"range":[139,33,139,49],"value":{"type":"literal","literal":"1px solid #aaa"}}]}},{"range":[139,53,139,76],"value":{"type":"tupled","tupled":[{"range":[139,55,139,66],"value":{"type":"literal","literal":"marginTop"}},{"range":[139,68,139,74],"value":{"type":"literal","literal":"15px"}}]}}]}}]}}}}}}}],"expression":{"range":[141,9,148,14],"value":{"type":"application","application":[{"range":[141,9,141,12],"value":{"type":"functionOrValue","functionOrValue":{"moduleName":[],"name":"div"}}},{"range":[141,13,141,78],"value":{"type":"list","list":[{"range":[141,15,141,76],"value":{"type":"application","application":[{"range":[141,15,141,20],"value":{"type":"functionOrValue","functionOrValue":{"moduleName":[],"name":"style"}}},{"range":[141,21,141,76],"value":{"type":"list","list":[{"range":[141,23,141,46],"value":{"type":"tupled","tupled":[{"range":[141,25,141,36],"value":{"type":"literal","literal":"marginTop"}},{"range":[141,38,141,44],"value":{"type":"literal","literal":"50px"}}]}},{"range":[141,48,141,74],"value":{"type":"tupled","tupled":[{"range":[141,50,141,60],"value":{"type":"literal","literal":"position"}},{"range":[141,62,141,72],"value":{"type":"literal","literal":"relative"}}]}}]}}]}}]}},{"range":[142,13,148,14],"value":{"type":"list","list":[{"range":[142,15,142,34],"value":{"type":"application","application":[{"range":[142,15,142,17],"value":{"type":"functionOrValue","functionOrValue":{"moduleName":[],"name":"hr"}}},{"range":[142,18,142,31],"value":{"type":"list","list":[{"range":[142,20,142,29],"value":{"type":"functionOrValue","functionOrValue":{"moduleName":[],"name":"lineStyle"}}}]}},{"range":[142,32,142,34],"value":{"type":"list","list":[]}}]}},{"range":[143,15,143,34],"value":{"type":"application","application":[{"range":[143,15,143,17],"value":{"type":"functionOrValue","functionOrValue":{"moduleName":[],"name":"hr"}}},{"range":[143,18,143,31],"value":{"type":"list","list":[{"range":[143,20,143,29],"value":{"type":"functionOrValue","functionOrValue":{"moduleName":[],"name":"lineStyle"}}}]}},{"range":[143,32,143,34],"value":{"type":"list","list":[]}}]}},{"range":[144,15,144,34],"value":{"type":"application","application":[{"range":[144,15,144,17],"value":{"type":"functionOrValue","functionOrValue":{"moduleName":[],"name":"hr"}}},{"range":[144,18,144,31],"value":{"type":"list","list":[{"range":[144,20,144,29],"value":{"type":"functionOrValue","functionOrValue":{"moduleName":[],"name":"lineStyle"}}}]}},{"range":[144,32,144,34],"value":{"type":"list","list":[]}}]}},{"range":[145,15,145,34],"value":{"type":"application","application":[{"range":[145,15,145,17],"value":{"type":"functionOrValue","functionOrValue":{"moduleName":[],"name":"hr"}}},{"range":[145,18,145,31],"value":{"type":"list","list":[{"range":[145,20,145,29],"value":{"type":"functionOrValue","functionOrValue":{"moduleName":[],"name":"lineStyle"}}}]}},{"range":[145,32,145,34],"value":{"type":"list","list":[]}}]}},{"range":[146,15,146,34],"value":{"type":"application","application":[{"range":[146,15,146,17],"value":{"type":"functionOrValue","functionOrValue":{"moduleName":[],"name":"hr"}}},{"range":[146,18,146,31],"value":{"type":"list","list":[{"range":[146,20,146,29],"value":{"type":"functionOrValue","functionOrValue":{"moduleName":[],"name":"lineStyle"}}}]}},{"range":[146,32,146,34],"value":{"type":"list","list":[]}}]}},{"range":[147,15,147,34],"value":{"type":"application","application":[{"range":[147,15,147,17],"value":{"type":"functionOrValue","functionOrValue":{"moduleName":[],"name":"hr"}}},{"range":[147,18,147,31],"value":{"type":"list","list":[{"range":[147,20,147,29],"value":{"type":"functionOrValue","functionOrValue":{"moduleName":[],"name":"lineStyle"}}}]}},{"range":[147,32,147,34],"value":{"type":"list","list":[]}}]}}]}}]}}}}}}}}}},{"range":[151,1,167,11],"value":{"type":"function","function":{"documentation":null,"signature":{"range":[151,1,151,20],"value":{"name":{"range":[151,1,151,9],"value":"tabInput"},"typeAnnotation":{"range":[151,12,151,20],"value":{"type":"typed","typed":{"moduleNameAndName":{"range":[151,12,151,16],"value":{"moduleName":[],"name":"Html"}},"args":[{"range":[151,17,151,20],"value":{"type":"typed","typed":{"moduleNameAndName":{"range":[151,17,151,20],"value":{"moduleName":[],"name":"Msg"}},"args":[]}}}]}}}}},"declaration":{"range":[152,1,167,11],"value":{"name":{"range":[152,1,152,9],"value":"tabInput"},"arguments":[],"expression":{"range":[153,5,167,11],"value":{"type":"application","application":[{"range":[153,5,153,13],"value":{"type":"functionOrValue","functionOrValue":{"moduleName":[],"name":"textarea"}}},{"range":[154,9,166,10],"value":{"type":"list","list":[{"range":[154,11,154,34],"value":{"type":"application","application":[{"range":[154,11,154,22],"value":{"type":"functionOrValue","functionOrValue":{"moduleName":[],"name":"placeholder"}}},{"range":[154,23,154,34],"value":{"type":"literal","literal":"Enter Tab"}}]}},{"range":[155,11,155,26],"value":{"type":"application","application":[{"range":[155,11,155,18],"value":{"type":"functionOrValue","functionOrValue":{"moduleName":[],"name":"onInput"}}},{"range":[155,19,155,26],"value":{"type":"functionOrValue","functionOrValue":{"moduleName":[],"name":"ReadTab"}}}]}},{"range":[156,11,165,14],"value":{"type":"application","application":[{"range":[156,11,156,16],"value":{"type":"functionOrValue","functionOrValue":{"moduleName":[],"name":"style"}}},{"range":[157,13,165,14],"value":{"type":"list","list":[{"range":[157,15,157,33],"value":{"type":"tupled","tupled":[{"range":[157,17,157,24],"value":{"type":"literal","literal":"width"}},{"range":[157,26,157,31],"value":{"type":"literal","literal":"60%"}}]}},{"range":[158,15,158,36],"value":{"type":"tupled","tupled":[{"range":[158,17,158,25],"value":{"type":"literal","literal":"height"}},{"range":[158,27,158,34],"value":{"type":"literal","literal":"100px"}}]}},{"range":[159,15,159,40],"value":{"type":"tupled","tupled":[{"range":[159,17,159,28],"value":{"type":"literal","literal":"textAlign"}},{"range":[159,30,159,38],"value":{"type":"literal","literal":"center"}}]}},{"range":[160,15,160,42],"value":{"type":"tupled","tupled":[{"range":[160,17,160,25],"value":{"type":"literal","literal":"margin"}},{"range":[160,27,160,40],"value":{"type":"literal","literal":"100px 20% 0"}}]}},{"range":[161,15,161,44],"value":{"type":"tupled","tupled":[{"range":[161,17,161,34],"value":{"type":"literal","literal":"backgroundColor"}},{"range":[161,36,161,42],"value":{"type":"literal","literal":"#fff"}}]}},{"range":[162,15,162,37],"value":{"type":"tupled","tupled":[{"range":[162,17,162,24],"value":{"type":"literal","literal":"color"}},{"range":[162,26,162,35],"value":{"type":"literal","literal":"#03a9f4"}}]}},{"range":[163,15,163,45],"value":{"type":"tupled","tupled":[{"range":[163,17,163,25],"value":{"type":"literal","literal":"border"}},{"range":[163,27,163,43],"value":{"type":"literal","literal":"1px solid #aaa"}}]}},{"range":[164,15,164,37],"value":{"type":"tupled","tupled":[{"range":[164,17,164,27],"value":{"type":"literal","literal":"fontSize"}},{"range":[164,29,164,35],"value":{"type":"literal","literal":"16px"}}]}}]}}]}}]}},{"range":[167,9,167,11],"value":{"type":"list","list":[]}}]}}}}}}},{"range":[170,1,172,180],"value":{"type":"function","function":{"documentation":null,"signature":{"range":[170,1,170,23],"value":{"name":{"range":[170,1,170,12],"value":"clearButton"},"typeAnnotation":{"range":[170,15,170,23],"value":{"type":"typed","typed":{"moduleNameAndName":{"range":[170,15,170,19],"value":{"moduleName":[],"name":"Html"}},"args":[{"range":[170,20,170,23],"value":{"type":"typed","typed":{"moduleNameAndName":{"range":[170,20,170,23],"value":{"moduleName":[],"name":"Msg"}},"args":[]}}}]}}}}},"declaration":{"range":[171,1,172,180],"value":{"name":{"range":[171,1,171,12],"value":"clearButton"},"arguments":[],"expression":{"range":[172,5,172,180],"value":{"type":"application","application":[{"range":[172,5,172,11],"value":{"type":"functionOrValue","functionOrValue":{"moduleName":[],"name":"button"}}},{"range":[172,12,172,159],"value":{"type":"list","list":[{"range":[172,14,172,157],"value":{"type":"application","application":[{"range":[172,14,172,19],"value":{"type":"functionOrValue","functionOrValue":{"moduleName":[],"name":"style"}}},{"range":[172,20,172,157],"value":{"type":"list","list":[{"range":[172,22,172,51],"value":{"type":"tupled","tupled":[{"range":[172,24,172,41],"value":{"type":"literal","literal":"backgroundColor"}},{"range":[172,43,172,49],"value":{"type":"literal","literal":"#ccc"}}]}},{"range":[172,53,172,75],"value":{"type":"tupled","tupled":[{"range":[172,55,172,62],"value":{"type":"literal","literal":"color"}},{"range":[172,64,172,73],"value":{"type":"literal","literal":"#03a9f4"}}]}},{"range":[172,77,172,107],"value":{"type":"tupled","tupled":[{"range":[172,79,172,87],"value":{"type":"literal","literal":"border"}},{"range":[172,89,172,105],"value":{"type":"literal","literal":"1px solid #aaa"}}]}},{"range":[172,109,172,132],"value":{"type":"tupled","tupled":[{"range":[172,111,172,122],"value":{"type":"literal","literal":"marginTop"}},{"range":[172,124,172,130],"value":{"type":"literal","literal":"10px"}}]}},{"range":[172,134,172,155],"value":{"type":"tupled","tupled":[{"range":[172,136,172,145],"value":{"type":"literal","literal":"padding"}},{"range":[172,147,172,153],"value":{"type":"literal","literal":"10px"}}]}}]}}]}}]}},{"range":[172,160,172,180],"value":{"type":"list","list":[{"range":[172,162,172,178],"value":{"type":"application","application":[{"range":[172,162,172,166],"value":{"type":"functionOrValue","functionOrValue":{"moduleName":[],"name":"text"}}},{"range":[172,167,172,178],"value":{"type":"literal","literal":"Clear Tab"}}]}}]}}]}}}}}}},{"range":[177,1,179,33],"value":{"type":"function","function":{"documentation":null,"signature":{"range":[177,1,177,44],"value":{"name":{"range":[177,1,177,11],"value":"parseInput"},"typeAnnotation":{"range":[177,14,177,44],"value":{"type":"function","function":{"left":{"range":[177,14,177,25],"value":{"type":"typed","typed":{"moduleNameAndName":{"range":[177,14,177,18],"value":{"moduleName":[],"name":"List"}},"args":[{"range":[177,19,177,25],"value":{"type":"typed","typed":{"moduleNameAndName":{"range":[177,19,177,25],"value":{"moduleName":[],"name":"String"}},"args":[]}}}]}}},"right":{"range":[177,29,177,44],"value":{"type":"typed","typed":{"moduleNameAndName":{"range":[177,29,177,33],"value":{"moduleName":[],"name":"List"}},"args":[{"range":[177,34,177,44],"value":{"type":"typed","typed":{"moduleNameAndName":{"range":[177,35,177,39],"value":{"moduleName":[],"name":"List"}},"args":[{"range":[177,40,177,43],"value":{"type":"typed","typed":{"moduleNameAndName":{"range":[177,40,177,43],"value":{"moduleName":[],"name":"Tab"}},"args":[]}}}]}}}]}}}}}}}},"declaration":{"range":[178,1,179,33],"value":{"name":{"range":[178,1,178,11],"value":"parseInput"},"arguments":[{"range":[178,12,178,20],"value":{"type":"var","var":{"value":"noteList"}}}],"expression":{"range":[179,5,179,33],"value":{"type":"application","application":[{"range":[179,5,179,13],"value":{"type":"functionOrValue","functionOrValue":{"moduleName":["List"],"name":"map"}}},{"range":[179,14,179,24],"value":{"type":"functionOrValue","functionOrValue":{"moduleName":[],"name":"splitNotes"}}},{"range":[179,25,179,33],"value":{"type":"functionOrValue","functionOrValue":{"moduleName":[],"name":"noteList"}}}]}}}}}}},{"range":[184,1,222,1],"value":{"type":"function","function":{"documentation":null,"signature":{"range":[184,1,184,32],"value":{"name":{"range":[184,1,184,11],"value":"splitNotes"},"typeAnnotation":{"range":[184,14,184,32],"value":{"type":"function","function":{"left":{"range":[184,14,184,20],"value":{"type":"typed","typed":{"moduleNameAndName":{"range":[184,14,184,20],"value":{"moduleName":[],"name":"String"}},"args":[]}}},"right":{"range":[184,24,184,32],"value":{"type":"typed","typed":{"moduleNameAndName":{"range":[184,24,184,28],"value":{"moduleName":[],"name":"List"}},"args":[{"range":[184,29,184,32],"value":{"type":"typed","typed":{"moduleNameAndName":{"range":[184,29,184,32],"value":{"moduleName":[],"name":"Tab"}},"args":[]}}}]}}}}}}}},"declaration":{"range":[185,1,222,1],"value":{"name":{"range":[185,1,185,11],"value":"splitNotes"},"arguments":[{"range":[185,12,185,16],"value":{"type":"var","var":{"value":"note"}}}],"expression":{"range":[186,5,222,1],"value":{"type":"ifBlock","ifBlock":{"clause":{"range":[186,8,186,32],"value":{"type":"application","application":[{"range":[186,8,186,21],"value":{"type":"functionOrValue","functionOrValue":{"moduleName":["String"],"name":"length"}}},{"range":[186,22,186,26],"value":{"type":"functionOrValue","functionOrValue":{"moduleName":[],"name":"note"}}},{"range":[186,27,186,29],"value":{"type":"operator","operator":"=="}},{"range":[186,30,186,32],"value":{"type":"integer","integer":12}}]}},"then":{"range":[187,9,210,5],"value":{"type":"let","let":{"declarations":[{"range":[188,13,191,13],"value":{"type":"function","function":{"documentation":null,"signature":null,"declaration":{"range":[188,13,189,38],"value":{"name":{"range":[188,13,188,15],"value":"e6"},"arguments":[],"expression":{"range":[189,17,189,38],"value":{"type":"application","application":[{"range":[189,17,189,29],"value":{"type":"functionOrValue","functionOrValue":{"moduleName":["String"],"name":"slice"}}},{"range":[189,30,189,31],"value":{"type":"integer","integer":0}},{"range":[189,32,189,33],"value":{"type":"integer","integer":2}},{"range":[189,34,189,38],"value":{"type":"functionOrValue","functionOrValue":{"moduleName":[],"name":"note"}}}]}}}}}}},{"range":[191,13,194,13],"value":{"type":"function","function":{"documentation":null,"signature":null,"declaration":{"range":[191,13,192,38],"value":{"name":{"range":[191,13,191,14],"value":"a"},"arguments":[],"expression":{"range":[192,17,192,38],"value":{"type":"application","application":[{"range":[192,17,192,29],"value":{"type":"functionOrValue","functionOrValue":{"moduleName":["String"],"name":"slice"}}},{"range":[192,30,192,31],"value":{"type":"integer","integer":2}},{"range":[192,32,192,33],"value":{"type":"integer","integer":4}},{"range":[192,34,192,38],"value":{"type":"functionOrValue","functionOrValue":{"moduleName":[],"name":"note"}}}]}}}}}}},{"range":[194,13,197,13],"value":{"type":"function","function":{"documentation":null,"signature":null,"declaration":{"range":[194,13,195,38],"value":{"name":{"range":[194,13,194,14],"value":"d"},"arguments":[],"expression":{"range":[195,17,195,38],"value":{"type":"application","application":[{"range":[195,17,195,29],"value":{"type":"functionOrValue","functionOrValue":{"moduleName":["String"],"name":"slice"}}},{"range":[195,30,195,31],"value":{"type":"integer","integer":4}},{"range":[195,32,195,33],"value":{"type":"integer","integer":6}},{"range":[195,34,195,38],"value":{"type":"functionOrValue","functionOrValue":{"moduleName":[],"name":"note"}}}]}}}}}}},{"range":[197,13,200,13],"value":{"type":"function","function":{"documentation":null,"signature":null,"declaration":{"range":[197,13,198,38],"value":{"name":{"range":[197,13,197,14],"value":"g"},"arguments":[],"expression":{"range":[198,17,198,38],"value":{"type":"application","application":[{"range":[198,17,198,29],"value":{"type":"functionOrValue","functionOrValue":{"moduleName":["String"],"name":"slice"}}},{"range":[198,30,198,31],"value":{"type":"integer","integer":6}},{"range":[198,32,198,33],"value":{"type":"integer","integer":8}},{"range":[198,34,198,38],"value":{"type":"functionOrValue","functionOrValue":{"moduleName":[],"name":"note"}}}]}}}}}}},{"range":[200,13,203,13],"value":{"type":"function","function":{"documentation":null,"signature":null,"declaration":{"range":[200,13,201,39],"value":{"name":{"range":[200,13,200,14],"value":"b"},"arguments":[],"expression":{"range":[201,17,201,39],"value":{"type":"application","application":[{"range":[201,17,201,29],"value":{"type":"functionOrValue","functionOrValue":{"moduleName":["String"],"name":"slice"}}},{"range":[201,30,201,31],"value":{"type":"integer","integer":8}},{"range":[201,32,201,34],"value":{"type":"integer","integer":10}},{"range":[201,35,201,39],"value":{"type":"functionOrValue","functionOrValue":{"moduleName":[],"name":"note"}}}]}}}}}}},{"range":[203,13,206,13],"value":{"type":"function","function":{"documentation":null,"signature":null,"declaration":{"range":[203,13,204,40],"value":{"name":{"range":[203,13,203,14],"value":"e"},"arguments":[],"expression":{"range":[204,17,204,40],"value":{"type":"application","application":[{"range":[204,17,204,29],"value":{"type":"functionOrValue","functionOrValue":{"moduleName":["String"],"name":"slice"}}},{"range":[204,30,204,32],"value":{"type":"integer","integer":10}},{"range":[204,33,204,35],"value":{"type":"integer","integer":12}},{"range":[204,36,204,40],"value":{"type":"functionOrValue","functionOrValue":{"moduleName":[],"name":"note"}}}]}}}}}}},{"range":[206,13,208,9],"value":{"type":"function","function":{"documentation":null,"signature":null,"declaration":{"range":[206,13,207,44],"value":{"name":{"range":[206,13,206,19],"value":"mapper"},"arguments":[{"range":[206,20,206,21],"value":{"type":"var","var":{"value":"a"}}}],"expression":{"range":[207,17,207,44],"value":{"type":"application","application":[{"range":[207,17,207,20],"value":{"type":"functionOrValue","functionOrValue":{"moduleName":[],"name":"Tab"}}},{"range":[207,21,207,31],"value":{"type":"parenthesized","parenthesized":{"range":[207,22,207,30],"value":{"type":"application","application":[{"range":[207,22,207,28],"value":{"type":"functionOrValue","functionOrValue":{"moduleName":[],"name":"fretNo"}}},{"range":[207,29,207,30],"value":{"type":"functionOrValue","functionOrValue":{"moduleName":[],"name":"a"}}}]}}}},{"range":[207,32,207,44],"value":{"type":"parenthesized","parenthesized":{"range":[207,33,207,43],"value":{"type":"application","application":[{"range":[207,33,207,41],"value":{"type":"functionOrValue","functionOrValue":{"moduleName":[],"name":"stringNo"}}},{"range":[207,42,207,43],"value":{"type":"functionOrValue","functionOrValue":{"moduleName":[],"name":"a"}}}]}}}}]}}}}}}}],"expression":{"range":[209,13,209,50],"value":{"type":"application","application":[{"range":[209,13,209,21],"value":{"type":"functionOrValue","functionOrValue":{"moduleName":["List"],"name":"map"}}},{"range":[209,22,209,28],"value":{"type":"functionOrValue","functionOrValue":{"moduleName":[],"name":"mapper"}}},{"range":[209,29,209,50],"value":{"type":"list","list":[{"range":[209,31,209,33],"value":{"type":"functionOrValue","functionOrValue":{"moduleName":[],"name":"e6"}}},{"range":[209,35,209,36],"value":{"type":"functionOrValue","functionOrValue":{"moduleName":[],"name":"a"}}},{"range":[209,38,209,39],"value":{"type":"functionOrValue","functionOrValue":{"moduleName":[],"name":"d"}}},{"range":[209,41,209,42],"value":{"type":"functionOrValue","functionOrValue":{"moduleName":[],"name":"g"}}},{"range":[209,44,209,45],"value":{"type":"functionOrValue","functionOrValue":{"moduleName":[],"name":"b"}}},{"range":[209,47,209,48],"value":{"type":"functionOrValue","functionOrValue":{"moduleName":[],"name":"e"}}}]}}]}}}}},"else":{"range":[210,10,222,1],"value":{"type":"ifBlock","ifBlock":{"clause":{"range":[210,13,210,68],"value":{"type":"application","application":[{"range":[210,13,210,26],"value":{"type":"functionOrValue","functionOrValue":{"moduleName":["String"],"name":"length"}}},{"range":[210,27,210,31],"value":{"type":"functionOrValue","functionOrValue":{"moduleName":[],"name":"note"}}},{"range":[210,32,210,34],"value":{"type":"operator","operator":"=="}},{"range":[210,35,210,36],"value":{"type":"integer","integer":1}},{"range":[210,37,210,39],"value":{"type":"operator","operator":"||"}},{"range":[210,40,210,52],"value":{"type":"functionOrValue","functionOrValue":{"moduleName":["String"],"name":"slice"}}},{"range":[210,53,210,54],"value":{"type":"integer","integer":1}},{"range":[210,55,210,56],"value":{"type":"integer","integer":2}},{"range":[210,57,210,61],"value":{"type":"functionOrValue","functionOrValue":{"moduleName":[],"name":"note"}}},{"range":[210,62,210,64],"value":{"type":"operator","operator":"=="}},{"range":[210,65,210,68],"value":{"type":"literal","literal":"#"}}]}},"then":{"range":[211,9,216,5],"value":{"type":"let","let":{"declarations":[{"range":[212,13,214,9],"value":{"type":"function","function":{"documentation":null,"signature":null,"declaration":{"range":[212,13,213,44],"value":{"name":{"range":[212,13,212,19],"value":"mapper"},"arguments":[{"range":[212,20,212,21],"value":{"type":"var","var":{"value":"a"}}}],"expression":{"range":[213,17,213,44],"value":{"type":"application","application":[{"range":[213,17,213,20],"value":{"type":"functionOrValue","functionOrValue":{"moduleName":[],"name":"Tab"}}},{"range":[213,21,213,31],"value":{"type":"parenthesized","parenthesized":{"range":[213,22,213,30],"value":{"type":"application","application":[{"range":[213,22,213,28],"value":{"type":"functionOrValue","functionOrValue":{"moduleName":[],"name":"fretNo"}}},{"range":[213,29,213,30],"value":{"type":"functionOrValue","functionOrValue":{"moduleName":[],"name":"a"}}}]}}}},{"range":[213,32,213,44],"value":{"type":"parenthesized","parenthesized":{"range":[213,33,213,43],"value":{"type":"application","application":[{"range":[213,33,213,41],"value":{"type":"functionOrValue","functionOrValue":{"moduleName":[],"name":"stringNo"}}},{"range":[213,42,213,43],"value":{"type":"functionOrValue","functionOrValue":{"moduleName":[],"name":"a"}}}]}}}}]}}}}}}}],"expression":{"range":[215,13,215,50],"value":{"type":"application","application":[{"range":[215,13,215,21],"value":{"type":"functionOrValue","functionOrValue":{"moduleName":["List"],"name":"map"}}},{"range":[215,22,215,28],"value":{"type":"functionOrValue","functionOrValue":{"moduleName":[],"name":"mapper"}}},{"range":[215,29,215,50],"value":{"type":"parenthesized","parenthesized":{"range":[215,30,215,49],"value":{"type":"application","application":[{"range":[215,30,215,44],"value":{"type":"functionOrValue","functionOrValue":{"moduleName":[],"name":"chordTransform"}}},{"range":[215,45,215,49],"value":{"type":"functionOrValue","functionOrValue":{"moduleName":[],"name":"note"}}}]}}}}]}}}}},"else":{"range":[217,9,217,46],"value":{"type":"list","list":[{"range":[217,11,217,44],"value":{"type":"application","application":[{"range":[217,11,217,14],"value":{"type":"functionOrValue","functionOrValue":{"moduleName":[],"name":"Tab"}}},{"range":[217,15,217,28],"value":{"type":"parenthesized","parenthesized":{"range":[217,16,217,27],"value":{"type":"application","application":[{"range":[217,16,217,22],"value":{"type":"functionOrValue","functionOrValue":{"moduleName":[],"name":"fretNo"}}},{"range":[217,23,217,27],"value":{"type":"functionOrValue","functionOrValue":{"moduleName":[],"name":"note"}}}]}}}},{"range":[217,29,217,44],"value":{"type":"parenthesized","parenthesized":{"range":[217,30,217,43],"value":{"type":"application","application":[{"range":[217,30,217,38],"value":{"type":"functionOrValue","functionOrValue":{"moduleName":[],"name":"stringNo"}}},{"range":[217,39,217,43],"value":{"type":"functionOrValue","functionOrValue":{"moduleName":[],"name":"note"}}}]}}}}]}}]}}}}}}}}}}}}},{"range":[222,1,226,33],"value":{"type":"function","function":{"documentation":null,"signature":{"range":[222,1,222,23],"value":{"name":{"range":[222,1,222,7],"value":"fretNo"},"typeAnnotation":{"range":[222,10,222,23],"value":{"type":"function","function":{"left":{"range":[222,10,222,16],"value":{"type":"typed","typed":{"moduleNameAndName":{"range":[222,10,222,16],"value":{"moduleName":[],"name":"String"}},"args":[]}}},"right":{"range":[222,20,222,23],"value":{"type":"typed","typed":{"moduleNameAndName":{"range":[222,20,222,23],"value":{"moduleName":[],"name":"Int"}},"args":[]}}}}}}}},"declaration":{"range":[223,1,226,33],"value":{"name":{"range":[223,1,223,7],"value":"fretNo"},"arguments":[{"range":[223,8,223,9],"value":{"type":"var","var":{"value":"a"}}}],"expression":{"range":[224,5,226,33],"value":{"type":"application","application":[{"range":[224,5,224,20],"value":{"type":"functionOrValue","functionOrValue":{"moduleName":["String"],"name":"dropLeft"}}},{"range":[224,21,224,22],"value":{"type":"integer","integer":1}},{"range":[224,23,224,24],"value":{"type":"functionOrValue","functionOrValue":{"moduleName":[],"name":"a"}}},{"range":[225,9,225,11],"value":{"type":"operator","operator":"|>"}},{"range":[225,12,225,24],"value":{"type":"functionOrValue","functionOrValue":{"moduleName":["String"],"name":"toInt"}}},{"range":[226,9,226,11],"value":{"type":"operator","operator":"|>"}},{"range":[226,12,226,30],"value":{"type":"functionOrValue","functionOrValue":{"moduleName":["Result"],"name":"withDefault"}}},{"range":[226,31,226,33],"value":{"type":"integer","integer":50}}]}}}}}}},{"range":[231,1,235,32],"value":{"type":"function","function":{"documentation":null,"signature":{"range":[231,1,231,25],"value":{"name":{"range":[231,1,231,9],"value":"stringNo"},"typeAnnotation":{"range":[231,12,231,25],"value":{"type":"function","function":{"left":{"range":[231,12,231,18],"value":{"type":"typed","typed":{"moduleNameAndName":{"range":[231,12,231,18],"value":{"moduleName":[],"name":"String"}},"args":[]}}},"right":{"range":[231,22,231,25],"value":{"type":"typed","typed":{"moduleNameAndName":{"range":[231,22,231,25],"value":{"moduleName":[],"name":"Int"}},"args":[]}}}}}}}},"declaration":{"range":[232,1,235,32],"value":{"name":{"range":[232,1,232,9],"value":"stringNo"},"arguments":[{"range":[232,10,232,11],"value":{"type":"var","var":{"value":"a"}}}],"expression":{"range":[233,5,235,32],"value":{"type":"application","application":[{"range":[233,5,233,16],"value":{"type":"functionOrValue","functionOrValue":{"moduleName":["String"],"name":"left"}}},{"range":[233,17,233,18],"value":{"type":"integer","integer":1}},{"range":[233,19,233,20],"value":{"type":"functionOrValue","functionOrValue":{"moduleName":[],"name":"a"}}},{"range":[234,9,234,11],"value":{"type":"operator","operator":"|>"}},{"range":[234,12,234,24],"value":{"type":"functionOrValue","functionOrValue":{"moduleName":["String"],"name":"toInt"}}},{"range":[235,9,235,11],"value":{"type":"operator","operator":"|>"}},{"range":[235,12,235,30],"value":{"type":"functionOrValue","functionOrValue":{"moduleName":["Result"],"name":"withDefault"}}},{"range":[235,31,235,32],"value":{"type":"integer","integer":0}}]}}}}}}},{"range":[238,1,260,16],"value":{"type":"function","function":{"documentation":null,"signature":{"range":[238,1,238,25],"value":{"name":{"range":[238,1,238,9],"value":"noteXpos"},"typeAnnotation":{"range":[238,12,238,25],"value":{"type":"function","function":{"left":{"range":[238,12,238,15],"value":{"type":"typed","typed":{"moduleNameAndName":{"range":[238,12,238,15],"value":{"moduleName":[],"name":"Int"}},"args":[]}}},"right":{"range":[238,19,238,25],"value":{"type":"typed","typed":{"moduleNameAndName":{"range":[238,19,238,25],"value":{"moduleName":[],"name":"String"}},"args":[]}}}}}}}},"declaration":{"range":[239,1,260,16],"value":{"name":{"range":[239,1,239,9],"value":"noteXpos"},"arguments":[{"range":[239,10,239,11],"value":{"type":"var","var":{"value":"a"}}}],"expression":{"range":[240,5,260,16],"value":{"type":"case","case":{"cases":[{"pattern":{"range":[241,9,241,10],"value":{"type":"int","int":{"value":1}}},"expression":{"range":[242,13,242,19],"value":{"type":"literal","literal":"-2px"}}},{"pattern":{"range":[244,9,244,10],"value":{"type":"int","int":{"value":2}}},"expression":{"range":[245,13,245,19],"value":{"type":"literal","literal":"15px"}}},{"pattern":{"range":[247,9,247,10],"value":{"type":"int","int":{"value":3}}},"expression":{"range":[248,13,248,19],"value":{"type":"literal","literal":"32px"}}},{"pattern":{"range":[250,9,250,10],"value":{"type":"int","int":{"value":4}}},"expression":{"range":[251,13,251,19],"value":{"type":"literal","literal":"49px"}}},{"pattern":{"range":[253,9,253,10],"value":{"type":"int","int":{"value":5}}},"expression":{"range":[254,13,254,19],"value":{"type":"literal","literal":"66px"}}},{"pattern":{"range":[256,9,256,10],"value":{"type":"int","int":{"value":6}}},"expression":{"range":[257,13,257,19],"value":{"type":"literal","literal":"83px"}}},{"pattern":{"range":[259,9,259,10],"value":{"type":"all","all":{}}},"expression":{"range":[260,13,260,16],"value":{"type":"literal","literal":"0"}}}],"expression":{"range":[240,10,240,11],"value":{"type":"functionOrValue","functionOrValue":{"moduleName":[],"name":"a"}}}}}}}}}}},{"range":[265,1,305,15],"value":{"type":"function","function":{"documentation":null,"signature":{"range":[265,1,265,39],"value":{"name":{"range":[265,1,265,15],"value":"chordTransform"},"typeAnnotation":{"range":[265,18,265,39],"value":{"type":"function","function":{"left":{"range":[265,18,265,24],"value":{"type":"typed","typed":{"moduleNameAndName":{"range":[265,18,265,24],"value":{"moduleName":[],"name":"String"}},"args":[]}}},"right":{"range":[265,28,265,39],"value":{"type":"typed","typed":{"moduleNameAndName":{"range":[265,28,265,32],"value":{"moduleName":[],"name":"List"}},"args":[{"range":[265,33,265,39],"value":{"type":"typed","typed":{"moduleNameAndName":{"range":[265,33,265,39],"value":{"moduleName":[],"name":"String"}},"args":[]}}}]}}}}}}}},"declaration":{"range":[266,1,305,15],"value":{"name":{"range":[266,1,266,15],"value":"chordTransform"},"arguments":[{"range":[266,16,266,20],"value":{"type":"var","var":{"value":"note"}}}],"expression":{"range":[267,5,305,15],"value":{"type":"case","case":{"cases":[{"pattern":{"range":[268,9,268,12],"value":{"type":"string","string":{"value":"A"}}},"expression":{"range":[269,13,269,51],"value":{"type":"list","list":[{"range":[269,15,269,19],"value":{"type":"literal","literal":"xx"}},{"range":[269,21,269,25],"value":{"type":"literal","literal":"50"}},{"range":[269,27,269,31],"value":{"type":"literal","literal":"42"}},{"range":[269,33,269,37],"value":{"type":"literal","literal":"32"}},{"range":[269,39,269,43],"value":{"type":"literal","literal":"22"}},{"range":[269,45,269,49],"value":{"type":"literal","literal":"10"}}]}}},{"pattern":{"range":[271,9,271,12],"value":{"type":"string","string":{"value":"a"}}},"expression":{"range":[272,13,272,51],"value":{"type":"list","list":[{"range":[272,15,272,19],"value":{"type":"literal","literal":"xx"}},{"range":[272,21,272,25],"value":{"type":"literal","literal":"50"}},{"range":[272,27,272,31],"value":{"type":"literal","literal":"42"}},{"range":[272,33,272,37],"value":{"type":"literal","literal":"32"}},{"range":[272,39,272,43],"value":{"type":"literal","literal":"21"}},{"range":[272,45,272,49],"value":{"type":"literal","literal":"10"}}]}}},{"pattern":{"range":[274,9,274,13],"value":{"type":"string","string":{"value":"B7"}}},"expression":{"range":[275,13,275,51],"value":{"type":"list","list":[{"range":[275,15,275,19],"value":{"type":"literal","literal":"xx"}},{"range":[275,21,275,25],"value":{"type":"literal","literal":"52"}},{"range":[275,27,275,31],"value":{"type":"literal","literal":"41"}},{"range":[275,33,275,37],"value":{"type":"literal","literal":"32"}},{"range":[275,39,275,43],"value":{"type":"literal","literal":"20"}},{"range":[275,45,275,49],"value":{"type":"literal","literal":"12"}}]}}},{"pattern":{"range":[277,9,277,12],"value":{"type":"string","string":{"value":"b"}}},"expression":{"range":[278,13,278,51],"value":{"type":"list","list":[{"range":[278,15,278,19],"value":{"type":"literal","literal":"xx"}},{"range":[278,21,278,25],"value":{"type":"literal","literal":"xx"}},{"range":[278,27,278,31],"value":{"type":"literal","literal":"44"}},{"range":[278,33,278,37],"value":{"type":"literal","literal":"34"}},{"range":[278,39,278,43],"value":{"type":"literal","literal":"23"}},{"range":[278,45,278,49],"value":{"type":"literal","literal":"12"}}]}}},{"pattern":{"range":[280,9,280,12],"value":{"type":"string","string":{"value":"C"}}},"expression":{"range":[281,13,281,51],"value":{"type":"list","list":[{"range":[281,15,281,19],"value":{"type":"literal","literal":"xx"}},{"range":[281,21,281,25],"value":{"type":"literal","literal":"53"}},{"range":[281,27,281,31],"value":{"type":"literal","literal":"42"}},{"range":[281,33,281,37],"value":{"type":"literal","literal":"30"}},{"range":[281,39,281,43],"value":{"type":"literal","literal":"21"}},{"range":[281,45,281,49],"value":{"type":"literal","literal":"10"}}]}}},{"pattern":{"range":[283,9,283,12],"value":{"type":"string","string":{"value":"D"}}},"expression":{"range":[284,13,284,51],"value":{"type":"list","list":[{"range":[284,15,284,19],"value":{"type":"literal","literal":"xx"}},{"range":[284,21,284,25],"value":{"type":"literal","literal":"xx"}},{"range":[284,27,284,31],"value":{"type":"literal","literal":"40"}},{"range":[284,33,284,37],"value":{"type":"literal","literal":"32"}},{"range":[284,39,284,43],"value":{"type":"literal","literal":"23"}},{"range":[284,45,284,49],"value":{"type":"literal","literal":"12"}}]}}},{"pattern":{"range":[286,9,286,12],"value":{"type":"string","string":{"value":"d"}}},"expression":{"range":[287,13,287,51],"value":{"type":"list","list":[{"range":[287,15,287,19],"value":{"type":"literal","literal":"xx"}},{"range":[287,21,287,25],"value":{"type":"literal","literal":"xx"}},{"range":[287,27,287,31],"value":{"type":"literal","literal":"40"}},{"range":[287,33,287,37],"value":{"type":"literal","literal":"32"}},{"range":[287,39,287,43],"value":{"type":"literal","literal":"23"}},{"range":[287,45,287,49],"value":{"type":"literal","literal":"11"}}]}}},{"pattern":{"range":[289,9,289,12],"value":{"type":"string","string":{"value":"e"}}},"expression":{"range":[290,13,290,51],"value":{"type":"list","list":[{"range":[290,15,290,19],"value":{"type":"literal","literal":"60"}},{"range":[290,21,290,25],"value":{"type":"literal","literal":"52"}},{"range":[290,27,290,31],"value":{"type":"literal","literal":"42"}},{"range":[290,33,290,37],"value":{"type":"literal","literal":"30"}},{"range":[290,39,290,43],"value":{"type":"literal","literal":"20"}},{"range":[290,45,290,49],"value":{"type":"literal","literal":"10"}}]}}},{"pattern":{"range":[292,9,292,12],"value":{"type":"string","string":{"value":"E"}}},"expression":{"range":[293,13,293,51],"value":{"type":"list","list":[{"range":[293,15,293,19],"value":{"type":"literal","literal":"60"}},{"range":[293,21,293,25],"value":{"type":"literal","literal":"52"}},{"range":[293,27,293,31],"value":{"type":"literal","literal":"42"}},{"range":[293,33,293,37],"value":{"type":"literal","literal":"31"}},{"range":[293,39,293,43],"value":{"type":"literal","literal":"20"}},{"range":[293,45,293,49],"value":{"type":"literal","literal":"10"}}]}}},{"pattern":{"range":[295,9,295,12],"value":{"type":"string","string":{"value":"F"}}},"expression":{"range":[296,13,296,51],"value":{"type":"list","list":[{"range":[296,15,296,19],"value":{"type":"literal","literal":"xx"}},{"range":[296,21,296,25],"value":{"type":"literal","literal":"xx"}},{"range":[296,27,296,31],"value":{"type":"literal","literal":"43"}},{"range":[296,33,296,37],"value":{"type":"literal","literal":"32"}},{"range":[296,39,296,43],"value":{"type":"literal","literal":"21"}},{"range":[296,45,296,49],"value":{"type":"literal","literal":"10"}}]}}},{"pattern":{"range":[298,9,298,13],"value":{"type":"string","string":{"value":"f#"}}},"expression":{"range":[299,13,299,51],"value":{"type":"list","list":[{"range":[299,15,299,19],"value":{"type":"literal","literal":"62"}},{"range":[299,21,299,25],"value":{"type":"literal","literal":"50"}},{"range":[299,27,299,31],"value":{"type":"literal","literal":"40"}},{"range":[299,33,299,37],"value":{"type":"literal","literal":"32"}},{"range":[299,39,299,43],"value":{"type":"literal","literal":"22"}},{"range":[299,45,299,49],"value":{"type":"literal","literal":"10"}}]}}},{"pattern":{"range":[301,9,301,12],"value":{"type":"string","string":{"value":"G"}}},"expression":{"range":[302,13,302,51],"value":{"type":"list","list":[{"range":[302,15,302,19],"value":{"type":"literal","literal":"63"}},{"range":[302,21,302,25],"value":{"type":"literal","literal":"52"}},{"range":[302,27,302,31],"value":{"type":"literal","literal":"40"}},{"range":[302,33,302,37],"value":{"type":"literal","literal":"30"}},{"range":[302,39,302,43],"value":{"type":"literal","literal":"23"}},{"range":[302,45,302,49],"value":{"type":"literal","literal":"13"}}]}}},{"pattern":{"range":[304,9,304,10],"value":{"type":"all","all":{}}},"expression":{"range":[305,13,305,15],"value":{"type":"list","list":[]}}}],"expression":{"range":[267,10,267,14],"value":{"type":"functionOrValue","functionOrValue":{"moduleName":[],"name":"note"}}}}}}}}}}},{"range":[308,1,320,10],"value":{"type":"function","function":{"documentation":null,"signature":{"range":[308,1,308,24],"value":{"name":{"range":[308,1,308,13],"value":"instructions"},"typeAnnotation":{"range":[308,16,308,24],"value":{"type":"typed","typed":{"moduleNameAndName":{"range":[308,16,308,20],"value":{"moduleName":[],"name":"Html"}},"args":[{"range":[308,21,308,24],"value":{"type":"generic","generic":{"value":"msg"}}}]}}}}},"declaration":{"range":[309,1,320,10],"value":{"name":{"range":[309,1,309,13],"value":"instructions"},"arguments":[],"expression":{"range":[310,5,320,10],"value":{"type":"application","application":[{"range":[310,5,310,7],"value":{"type":"functionOrValue","functionOrValue":{"moduleName":[],"name":"ul"}}},{"range":[310,8,310,153],"value":{"type":"list","list":[{"range":[310,10,310,151],"value":{"type":"application","application":[{"range":[310,10,310,15],"value":{"type":"functionOrValue","functionOrValue":{"moduleName":[],"name":"style"}}},{"range":[310,16,310,151],"value":{"type":"list","list":[{"range":[310,18,310,44],"value":{"type":"tupled","tupled":[{"range":[310,20,310,30],"value":{"type":"literal","literal":"position"}},{"range":[310,32,310,42],"value":{"type":"literal","literal":"absolute"}}]}},{"range":[310,46,310,64],"value":{"type":"tupled","tupled":[{"range":[310,48,310,56],"value":{"type":"literal","literal":"bottom"}},{"range":[310,58,310,62],"value":{"type":"literal","literal":"5%"}}]}},{"range":[310,66,310,83],"value":{"type":"tupled","tupled":[{"range":[310,68,310,74],"value":{"type":"literal","literal":"left"}},{"range":[310,76,310,81],"value":{"type":"literal","literal":"25%"}}]}},{"range":[310,85,310,103],"value":{"type":"tupled","tupled":[{"range":[310,87,310,94],"value":{"type":"literal","literal":"width"}},{"range":[310,96,310,101],"value":{"type":"literal","literal":"60%"}}]}},{"range":[310,105,310,128],"value":{"type":"tupled","tupled":[{"range":[310,107,310,118],"value":{"type":"literal","literal":"textAlign"}},{"range":[310,120,310,126],"value":{"type":"literal","literal":"left"}}]}},{"range":[310,130,310,149],"value":{"type":"tupled","tupled":[{"range":[310,132,310,139],"value":{"type":"literal","literal":"color"}},{"range":[310,141,310,147],"value":{"type":"literal","literal":"#333"}}]}}]}}]}}]}},{"range":[311,9,320,10],"value":{"type":"list","list":[{"range":[311,11,311,122],"value":{"type":"application","application":[{"range":[311,11,311,13],"value":{"type":"functionOrValue","functionOrValue":{"moduleName":[],"name":"li"}}},{"range":[311,14,311,16],"value":{"type":"list","list":[]}},{"range":[311,17,311,122],"value":{"type":"list","list":[{"range":[311,19,311,120],"value":{"type":"application","application":[{"range":[311,19,311,23],"value":{"type":"functionOrValue","functionOrValue":{"moduleName":[],"name":"text"}}},{"range":[311,24,311,120],"value":{"type":"literal","literal":"type string number directly followed by fret number, followed by a space, ex: 10 21 33 11, etc"}}]}}]}}]}},{"range":[312,11,312,93],"value":{"type":"application","application":[{"range":[312,11,312,13],"value":{"type":"functionOrValue","functionOrValue":{"moduleName":[],"name":"li"}}},{"range":[312,14,312,16],"value":{"type":"list","list":[]}},{"range":[312,17,312,93],"value":{"type":"list","list":[{"range":[312,19,312,91],"value":{"type":"application","application":[{"range":[312,19,312,23],"value":{"type":"functionOrValue","functionOrValue":{"moduleName":[],"name":"text"}}},{"range":[312,24,312,91],"value":{"type":"literal","literal":"type space as many times as desired to add spacing between notes."}}]}}]}}]}},{"range":[313,11,313,117],"value":{"type":"application","application":[{"range":[313,11,313,13],"value":{"type":"functionOrValue","functionOrValue":{"moduleName":[],"name":"li"}}},{"range":[313,14,313,16],"value":{"type":"list","list":[]}},{"range":[313,17,313,117],"value":{"type":"list","list":[{"range":[313,19,313,115],"value":{"type":"application","application":[{"range":[313,19,313,23],"value":{"type":"functionOrValue","functionOrValue":{"moduleName":[],"name":"text"}}},{"range":[313,24,313,115],"value":{"type":"literal","literal":"for chords type all 6 string number/fret number sets together. ex: G major = 635240302313"}}]}}]}}]}},{"range":[314,11,314,115],"value":{"type":"application","application":[{"range":[314,11,314,13],"value":{"type":"functionOrValue","functionOrValue":{"moduleName":[],"name":"li"}}},{"range":[314,14,314,16],"value":{"type":"list","list":[]}},{"range":[314,17,314,115],"value":{"type":"list","list":[{"range":[314,19,314,113],"value":{"type":"application","application":[{"range":[314,19,314,23],"value":{"type":"functionOrValue","functionOrValue":{"moduleName":[],"name":"text"}}},{"range":[314,24,314,113],"value":{"type":"literal","literal":"for chords with fewer than 6 strings use xx for string/fret. ex: D major = xxxx40322312"}}]}}]}}]}},{"range":[315,11,315,96],"value":{"type":"application","application":[{"range":[315,11,315,13],"value":{"type":"functionOrValue","functionOrValue":{"moduleName":[],"name":"li"}}},{"range":[315,14,315,16],"value":{"type":"list","list":[]}},{"range":[315,17,315,96],"value":{"type":"list","list":[{"range":[315,19,315,94],"value":{"type":"application","application":[{"range":[315,19,315,23],"value":{"type":"functionOrValue","functionOrValue":{"moduleName":[],"name":"text"}}},{"range":[315,24,315,94],"value":{"type":"literal","literal":"OR... You can just enter a chord name: G fom G major; a for a minor."}}]}}]}}]}},{"range":[316,11,316,50],"value":{"type":"application","application":[{"range":[316,11,316,13],"value":{"type":"functionOrValue","functionOrValue":{"moduleName":[],"name":"li"}}},{"range":[316,14,316,16],"value":{"type":"list","list":[]}},{"range":[316,17,316,50],"value":{"type":"list","list":[{"range":[316,19,316,48],"value":{"type":"application","application":[{"range":[316,19,316,23],"value":{"type":"functionOrValue","functionOrValue":{"moduleName":[],"name":"text"}}},{"range":[316,24,316,48],"value":{"type":"literal","literal":"type 99 for a barline."}}]}}]}}]}},{"range":[317,11,317,57],"value":{"type":"application","application":[{"range":[317,11,317,13],"value":{"type":"functionOrValue","functionOrValue":{"moduleName":[],"name":"li"}}},{"range":[317,14,317,16],"value":{"type":"list","list":[]}},{"range":[317,17,317,57],"value":{"type":"list","list":[{"range":[317,19,317,55],"value":{"type":"application","application":[{"range":[317,19,317,23],"value":{"type":"functionOrValue","functionOrValue":{"moduleName":[],"name":"text"}}},{"range":[317,24,317,55],"value":{"type":"literal","literal":"type 88 for a double barline."}}]}}]}}]}},{"range":[318,11,318,123],"value":{"type":"application","application":[{"range":[318,11,318,13],"value":{"type":"functionOrValue","functionOrValue":{"moduleName":[],"name":"li"}}},{"range":[318,14,318,16],"value":{"type":"list","list":[]}},{"range":[318,17,318,123],"value":{"type":"list","list":[{"range":[318,19,318,121],"value":{"type":"application","application":[{"range":[318,19,318,23],"value":{"type":"functionOrValue","functionOrValue":{"moduleName":[],"name":"text"}}},{"range":[318,24,318,121],"value":{"type":"literal","literal":"type STRING 51 for a slur mark; 52 for / 53 for \\  So if I want forward slide on string 3, 352"}}]}}]}}]}},{"range":[319,11,319,59],"value":{"type":"application","application":[{"range":[319,11,319,13],"value":{"type":"functionOrValue","functionOrValue":{"moduleName":[],"name":"li"}}},{"range":[319,14,319,16],"value":{"type":"list","list":[]}},{"range":[319,17,319,59],"value":{"type":"list","list":[{"range":[319,19,319,57],"value":{"type":"application","application":[{"range":[319,19,319,23],"value":{"type":"functionOrValue","functionOrValue":{"moduleName":[],"name":"text"}}},{"range":[319,24,319,57],"value":{"type":"literal","literal":"Experimental, more coming soon!"}}]}}]}}]}}]}}]}}}}}}},{"range":[323,1,325,13],"value":{"type":"function","function":{"documentation":null,"signature":{"range":[323,1,323,29],"value":{"name":{"range":[323,1,323,14],"value":"subscriptions"},"typeAnnotation":{"range":[323,17,323,29],"value":{"type":"function","function":{"left":{"range":[323,17,323,18],"value":{"type":"generic","generic":{"value":"a"}}},"right":{"range":[323,22,323,29],"value":{"type":"typed","typed":{"moduleNameAndName":{"range":[323,22,323,25],"value":{"moduleName":[],"name":"Sub"}},"args":[{"range":[323,26,323,29],"value":{"type":"generic","generic":{"value":"msg"}}}]}}}}}}}},"declaration":{"range":[324,1,325,13],"value":{"name":{"range":[324,1,324,14],"value":"subscriptions"},"arguments":[{"range":[324,15,324,20],"value":{"type":"var","var":{"value":"model"}}}],"expression":{"range":[325,5,325,13],"value":{"type":"functionOrValue","functionOrValue":{"moduleName":["Sub"],"name":"none"}}}}}}}}],"comments":[{"range":[263,1,264,3],"value":"{-| Turns named chords (i.e. \"G\", \"C\", into Tab )\n-}"},{"range":[229,1,230,3],"value":"{-| Takes in a 2 digit fret/string no and splits out just the string\n-}"},{"range":[220,1,221,3],"value":"{-| Takes in a 2 digit fret/string no and splits out just the fret\n-}"},{"range":[182,1,183,3],"value":"{-| Determines if note is a fret/string combo, a chord, or a special symbol and formats accordingly\n-}"},{"range":[175,1,176,3],"value":"{-| Maps input over splitNotes to format\n-}"},{"range":[117,17,117,25],"value":"-- Chord"},{"range":[113,25,113,38],"value":"-- slide down"},{"range":[110,25,110,36],"value":"-- slide up"},{"range":[107,25,107,32],"value":"-- slur"},{"range":[104,25,104,39],"value":"-- double line"},{"range":[101,25,101,49],"value":"-- single line / bar end"},{"range":[91,13,91,27],"value":"-- Single note"},{"range":[85,1,86,3],"value":"{-| Takes in the list of notes that have been read in and processed and displays them as HTML.\n-}"}]}